pmemo/__init__.py
pmemo/api/__init__.py
pmemo/api/auth.py
pmemo/api/client.py
pmemo/api/config.py
pmemo/custom_select.py
pmemo/extensions/__init__.py
pmemo/extensions/base.py
pmemo/extensions/openai_completion.py
pmemo/extensions/prompt_template_manager.py
pmemo/main.py
pmemo/memo.py
pmemo/pmemo_editor.py
pmemo/preferences.py
pmemo/utils.py
pmemo-0.4.0.dist-info/LICENSE
pmemo-0.4.0.dist-info/METADATA
pmemo-0.4.0.dist-info/WHEEL
pmemo-0.4.0.dist-info/entry_points.txt
pmemo-0.4.0.dist-info/RECORD
