Metadata-Version: 2.1
Name: pmemo
Version: 0.4.0
Summary: Pmemo is a command-line memo editor designed for seamless editing directly in the terminal environment. It offers a range of features to enhance your memo-taking experience and leverages the power of OpenAI's ChatGPT.
Home-page: https://github.com/Asugawara/pmemo
License: MIT
Keywords: memo,TUI
Author: Asugawara
Author-email: asgasw@gmail.com
Requires-Python: >=3.9,<4.0
Classifier: License :: OSI Approved :: MIT License
Classifier: Programming Language :: Python
Classifier: Programming Language :: Python :: 3
Classifier: Programming Language :: Python :: 3.9
Classifier: Programming Language :: Python :: 3.10
Classifier: Programming Language :: Python :: 3.11
Classifier: Programming Language :: Python :: 3.12
Classifier: Programming Language :: Python :: 3 :: Only
Classifier: Programming Language :: Python :: Implementation :: PyPy
Requires-Dist: cryptography (>=42.0.2,<43.0.0)
Requires-Dist: logzero (>=1.7.0,<2.0.0)
Requires-Dist: openai (>=0.27.10,<0.28.0)
Requires-Dist: prompt-toolkit (>=3.0.43,<4.0.0)
Requires-Dist: pydantic (>=2.5.3,<3.0.0)
Requires-Dist: pygments (>=2.17.1,<3.0.0)
Requires-Dist: pyperclip (>=1.8.2,<2.0.0)
Requires-Dist: requests (>=2.31.0,<3.0.0)
Requires-Dist: rich (>=13.7.0,<14.0.0)
Project-URL: Repository, https://github.com/Asugawara/pmemo
